MANIFEST.in
README.md
malconf
setup.py
malwareconfig/__init__.py
malwareconfig/common.py
malwareconfig/crypto.py
malwareconfig/fileparser.py
malwareconfig/modules.py
malwareconfig/yarascanner.py
malwareconfig.egg-info/PKG-INFO
malwareconfig.egg-info/SOURCES.txt
malwareconfig.egg-info/dependency_links.txt
malwareconfig.egg-info/not-zip-safe
malwareconfig.egg-info/requires.txt
malwareconfig.egg-info/top_level.txt
malwareconfig/decoders/LostDoor.py
malwareconfig/decoders/Xtreme.py
malwareconfig/decoders/__init__.py
malwareconfig/decoders/aar.py
malwareconfig/decoders/adwind.py
malwareconfig/decoders/adzok.py
malwareconfig/decoders/alienspy.py
malwareconfig/decoders/alina.py
malwareconfig/decoders/arcom.py
malwareconfig/decoders/blacknix.py
malwareconfig/decoders/blackshades.py
malwareconfig/decoders/bluebanana.py
malwareconfig/decoders/bozok.py
malwareconfig/decoders/clientmesh.py
malwareconfig/decoders/cybergate.py
malwareconfig/decoders/darkcomet.py
malwareconfig/decoders/darkrat.py
malwareconfig/decoders/hawkeye.py
malwareconfig/decoders/hrat.py
malwareconfig/decoders/jbifrost.py
malwareconfig/decoders/jrat.py
malwareconfig/decoders/luminositylink.py
malwareconfig/decoders/luxnet.py
malwareconfig/decoders/mirai.py
malwareconfig/decoders/nanocore.py
malwareconfig/decoders/netwire.py
malwareconfig/decoders/njrat.py
malwareconfig/decoders/plasma.py
malwareconfig/decoders/remcos.py
malwareconfig/decoders/saefko.py
malwareconfig/decoders/sakula.py
malwareconfig/decoders/spynote.py
malwareconfig/decoders/template.py
malwareconfig/preprocessors/__init__.py
malwareconfig/preprocessors/upx.py
malwareconfig/yaraRules/AAR.yar
malwareconfig/yaraRules/Adzok.yar
malwareconfig/yaraRules/AlienSpy.yar
malwareconfig/yaraRules/Alina.yar
malwareconfig/yaraRules/Ap0calypse.yar
malwareconfig/yaraRules/Arcom.yar
malwareconfig/yaraRules/Bandook.yar
malwareconfig/yaraRules/BlackNix.yar
malwareconfig/yaraRules/BlackShades.yar
malwareconfig/yaraRules/BlueBanana.yar
malwareconfig/yaraRules/Bozok.yar
malwareconfig/yaraRules/ClientMesh.yar
malwareconfig/yaraRules/CyberGate.yar
malwareconfig/yaraRules/DarkComet.yar
malwareconfig/yaraRules/DarkRAT.yar
malwareconfig/yaraRules/Greame.yar
