Metadata-Version: 2.1
Name: malwareconfig
Version: 1.0.3
Summary: Malware Config Extraction
Home-page: https://malwareconfig.com
Author: Kevin Breen
Author-email: thehermit@malwareconfig.com
License: GNU V3
Platform: UNKNOWN
